[
    {
        "Start": "Berlin", 
        "Destination": "Stuttgart", 
        "Year": 2021,
        "Month": "05",
        "Day": 30,
        "Hours": 14, 
        "Minutes": 26,
        "Price": "85€",
        "Changes": "2",
        "Duration": "7h20",
    },  
    {
        "Start": "Berlin", 
        "Destination": "Stuttgart", 
        "Year": 2021,
        "Month": "05",
        "Day": 30,
        "Hours": 17, 
        "Minutes": 11,
        "Price": "73€", 
        "Changes": "1",
        "Duration": "6h42",
    },     
    {
        "Start": "Berlin", 
        "Destination": "Stuttgart", 
        "Year": 2021,
        "Month": "05",
        "Day": 29,
        "Hours": 11, 
        "Minutes": 49,
        "Price": "89€",
        "Changes": "4",
        "Duration": "8h10",
    },     
    {
        "Start": "Hamburg", 
        "Destination": "Konstanz", 
        "Year": 2021,
        "Month": "05",
        "Day": "02",
        "Hours": 13, 
        "Minutes": 21,
        "Price": "98€",
        "Changes": "4",
        "Duration": "6h14",
    }, 
    {
        "Start": "Hanover", 
        "Destination": "Frankfurt", 
        "Year": 2021,
        "Month": "06",
        "Day": "08",
        "Hours": 16, 
        "Minutes": "01",
        "Price": "46€", 
        "Changes": "1",
        "Duration": "3h45",
    },      
    {
        "Start": "Konstanz", 
        "Destination": "Munich", 
        "Year": 2021,
        "Month": "06",
        "Day": 28,
        "Hours": 11, 
        "Minutes": 41,
        "Price": "20€",
        "Changes": "2",
        "Duration": "3h55",
    },
    {
        "Start": "Konstanz", 
        "Destination": "Berlin", 
        "Year": 2021,
        "Month": "05",
        "Day": 14,
        "Hours": 14, 
        "Minutes": "07",
        "Price": "105€",
        "Changes": "3",
        "Duration": "9h11",
    },  
    {
        "Start": "Zürich", 
        "Destination": "Frankfurt", 
        "Year": 2021,
        "Month": "06",
        "Day": 15,
        "Hours": 19, 
        "Minutes": 18,
        "Price": "58€",
        "Changes": "1",
        "Duration": "5h51",
    },
    {
        "Start": "Berlin", 
        "Destination": "Hamburg", 
        "Year": 2021,
        "Month": "06",
        "Day": 25,
        "Hours": "06", 
        "Minutes": "08",
        "Price": "33€",
        "Changes": "0",
        "Duration": "2h34",
    }, 
    {
        "Start": "Konstanz", 
        "Destination": "Frankfurt", 
        "Year": 2021,
        "Month": "05",
        "Day": 25,
        "Hours": 12, 
        "Minutes": 09,
        "Price": "45€",
        "Changes": "2",
        "Duration": "5h02",
    },  
    {
        "Start": "Zürich", 
        "Destination": "Stuttgart", 
        "Year": 2021,
        "Month": "06",
        "Day": "01",
        "Hours": 19, 
        "Minutes": 18,
        "Price": "62€",
        "Changes": "0",
        "Duration": "0h56",
    },
    {
        "Start": "Konstanz", 
        "Destination": "Hamburg", 
        "Year": 2021,
        "Month": "06",
        "Day": 14,
        "Hours": 11, 
        "Minutes": 58,
        "Price": "55€",
        "Changes": "1",
        "Duration": "6h28",
    },
    {
        "Start": "Berlin", 
        "Destination": "Konstanz", 
        "Year": 2021,
        "Month": "05",
        "Day": 11,
        "Hours": 15, 
        "Minutes": 42,
        "Price": "72€",
        "Changes": "4",
        "Duration": "9h11",
    },
    {
        "Start": "Stuttgart", 
        "Destination": "Berlin", 
        "Year": 2021,
        "Month": "04",
        "Day": 29,
        "Hours": 18, 
        "Minutes": 11,
        "Price": "62€",
        "Changes": "3",
        "Duration": "8h09",
    },
    {
        "Start": "Paris", 
        "Destination": "Konstanz", 
        "Year": 2021,
        "Month": "06",
        "Day": 11,
        "Hours": "07", 
        "Minutes": 43,
        "Price": "70€",
        "Changes": "2",
        "Duration": "7h30",
    },
    {
        "Start": "Konstanz", 
        "Destination": "Berlin", 
        "Year": 2021,
        "Month": "05",
        "Day": 27,
        "Hours": "09", 
        "Minutes": "07",
        "Price": "43€",
        "Changes": "3",
        "Duration": "9h21",
    },
    {
        "Start": "Konstanz", 
        "Destination": "Hamburg", 
        "Year": 2021,
        "Month": "05",
        "Day": 28,
        "Hours": "13", 
        "Minutes": 22,
        "Price": "53€",
        "Changes": "1",
        "Duration": "7h58",
    },
    {
        "Start": "Konstanz", 
        "Destination": "Stuttgart", 
        "Year": 2021,
        "Month": "05",
        "Day": 26,
        "Hours": "14", 
        "Minutes": "05",
        "Price": "17€",
        "Changes": "2",
        "Duration": "3h35",
    },
    {
        "Start": "Konstanz", 
        "Destination": "Stuttgart", 
        "Year": 2021,
        "Month": "05",
        "Day": 26,
        "Hours": "17", 
        "Minutes": "53",
        "Price": "15€",
        "Changes": "1",
        "Duration": "3h23",
    },
    {
        "Start": "Konstanz", 
        "Destination": "Stuttgart", 
        "Year": 2021,
        "Month": "06",
        "Day": 26,
        "Hours": "21", 
        "Minutes": "01",
        "Price": "21€",
        "Changes": "3",
        "Duration": "3h46",
    }
]